clipzyme/__init__.py
clipzyme/callbacks/__init__.py
clipzyme/callbacks/basic.py
clipzyme/datasets/__init__.py
clipzyme/datasets/abstract.py
clipzyme/datasets/enzyme_screening.py
clipzyme/datasets/enzymemap.py
clipzyme/datasets/reaction.py
clipzyme/learning/losses/__init__.py
clipzyme/learning/losses/basic.py
clipzyme/learning/losses/contrastive.py
clipzyme/learning/metrics/__init__.py
clipzyme/learning/metrics/basic.py
clipzyme/learning/metrics/representation.py
clipzyme/learning/optimizers/__init__.py
clipzyme/learning/optimizers/basic.py
clipzyme/learning/schedulers/__init__.py
clipzyme/learning/schedulers/basic.py
clipzyme/learning/schedulers/warmup.py
clipzyme/learning/utils.py
clipzyme/lightning/__init__.py
clipzyme/lightning/base.py
clipzyme/lightning/clipzyme.py
clipzyme/loggers/__init__.py
clipzyme/loggers/tensorboard.py
clipzyme/loggers/wandb.py
clipzyme/models/__init__.py
clipzyme/models/abstract.py
clipzyme/models/chemprop.py
clipzyme/models/classifier.py
clipzyme/models/egnn.py
clipzyme/models/fair_esm.py
clipzyme/models/gat.py
clipzyme/models/protmol.py
clipzyme/models/seq2seq.py
clipzyme/models/wln.py
clipzyme/utils/__init__.py
clipzyme/utils/amino_acids.py
clipzyme/utils/callbacks.py
clipzyme/utils/classes.py
clipzyme/utils/colabfold_msa.py
clipzyme/utils/loading.py
clipzyme/utils/messages.py
clipzyme/utils/parsing.py
clipzyme/utils/protein_utils.py
clipzyme/utils/proteins.py
clipzyme/utils/pyg.py
clipzyme/utils/reactions.py
clipzyme/utils/registry.py
clipzyme/utils/sampler.py
clipzyme/utils/screening.py
clipzyme/utils/smiles.py
clipzyme/utils/wln_processing.py
clipzyme-0.0.12.dist-info/LICENSE.txt
clipzyme-0.0.12.dist-info/METADATA
clipzyme-0.0.12.dist-info/WHEEL
clipzyme-0.0.12.dist-info/RECORD
