Metadata-Version: 2.1
Name: clipzyme
Version: 0.0.12
Summary: Reaction-Conditioned Virtual Screening of Enzymes
Home-page: https://github.com/pgmikhael/clipzyme
License: Apache 2.0
Author: Peter G Mikhael
Author-email: pgmikhael@csail.mit.edu
Requires-Python: >=3.10,<3.11
Classifier: License :: Other/Proprietary License
Classifier: Programming Language :: Python :: 3
Classifier: Programming Language :: Python :: 3.10
Project-URL: Repository, https://github.com/pgmikhael/clipzyme
